anesto.py
anesto-1.0.dist-info/LICENSE
anesto-1.0.dist-info/METADATA
anesto-1.0.dist-info/WHEEL
anesto-1.0.dist-info/top_level.txt
anesto-1.0.dist-info/RECORD
