Metadata-Version: 2.1
Name: anesto
Version: 1.0
Summary: Akamai NetStorage API for Python
Home-page: https://github.com/psvz/anesto
Author: Vitaly Zuevsky
Author-email: vitaly.zuevsky@gmail.com
License: MIT
Platform: UNKNOWN
Classifier: Programming Language :: Python :: 3
Classifier: License :: OSI Approved :: MIT License
Classifier: Operating System :: OS Independent
Requires-Python: >=3.6
Requires-Dist: requests (>=2.21.0)
